aclpwn/__init__.py
aclpwn/__main__.py
aclpwn/database.py
aclpwn/exploitation.py
aclpwn/pathfinding.py
aclpwn/restore.py
aclpwn/utils.py
aclpwn-1.0.0.dist-info/DESCRIPTION.rst
aclpwn-1.0.0.dist-info/METADATA
aclpwn-1.0.0.dist-info/RECORD
aclpwn-1.0.0.dist-info/WHEEL
aclpwn-1.0.0.dist-info/entry_points.txt
aclpwn-1.0.0.dist-info/metadata.json
aclpwn-1.0.0.dist-info/top_level.txt
